python_youtube/__init__.py
python_youtube/youtube.py
async_python_youtube-0.1.0.dist-info/LICENSE.md
async_python_youtube-0.1.0.dist-info/METADATA
async_python_youtube-0.1.0.dist-info/WHEEL
async_python_youtube-0.1.0.dist-info/RECORD
