Metadata-Version: 2.1
Name: async-python-youtube
Version: 0.1.0
Summary: Asynchronous Python client for YouTube V3 API.
Home-page: https://github.com/joostlek/python-youtube
License: MIT
Keywords: youtube,api,async,client
Author: Joost Lekkerkerker
Author-email: joostlek@outlook.com
Maintainer: Joost Lekkerkerker
Maintainer-email: joostlek@outlook.com
Requires-Python: >=3.10,<4.0
Classifier: Development Status :: 5 - Production/Stable
Classifier: Framework :: AsyncIO
Classifier: Intended Audience :: Developers
Classifier: License :: OSI Approved :: MIT License
Classifier: Natural Language :: English
Classifier: Programming Language :: Python :: 3
Classifier: Programming Language :: Python :: 3.10
Classifier: Programming Language :: Python :: 3.11
Classifier: Topic :: Software Development :: Libraries :: Python Modules
Requires-Dist: aiohttp (>=3.0.0)
Requires-Dist: pydantic (>=1.10.8)
Requires-Dist: yarl (>=1.6.0)
Project-URL: Bug Tracker, https://github.com/joostlek/python-youtube/issues
Project-URL: Changelog, https://github.com/joostlek/python-youtube/releases
Project-URL: Documentation, https://github.com/joostlek/python-youtube
Project-URL: Repository, https://github.com/joostlek/python-youtube
